gitlogs/__init__.py
gitlogs/gitstats.py
gitlogs/main.py
gitlogs/parser.py
gitlogs/defaults/__init__.py
gitlogs/defaults/defaults.json
gitlogs/defaults/handle_defaults.py
gitlogs/utils/__init__.py
gitlogs/utils/bcolors.py
gitlogs/validate/__init__.py
gitlogs/validate/check_args.py
git_logs-0.1.0.dist-info/LICENSE
git_logs-0.1.0.dist-info/METADATA
git_logs-0.1.0.dist-info/WHEEL
git_logs-0.1.0.dist-info/entry_points.txt
git_logs-0.1.0.dist-info/top_level.txt
git_logs-0.1.0.dist-info/RECORD
