Metadata-Version: 2.1
Name: git-logs
Version: 0.1.0
Summary: Bird-eye view of a local git repository
Download-URL: https://github.com/nkilm/git-logs
Author: Nikhil Mohite
Author-email: nikhilmohitelhs@gmail.com
Keywords: python,git,statistics,local repository,git statistics
Classifier: Topic :: Utilities
Classifier: Intended Audience :: Developers
Classifier: Programming Language :: Python
Classifier: Natural Language :: English
Classifier: License :: OSI Approved :: MIT License
Classifier: Topic :: Software Development :: Version Control :: Git
Classifier: Programming Language :: Python :: 3
License-File: LICENSE
